farsi_tools/__init__.py
farsi_tools-0.2.dist-info/LICENSE
farsi_tools-0.2.dist-info/METADATA
farsi_tools-0.2.dist-info/WHEEL
farsi_tools-0.2.dist-info/top_level.txt
farsi_tools-0.2.dist-info/RECORD
