Metadata-Version: 2.1
Name: farsi-tools
Version: 0.2
Summary: Farsi Tools: Tools for processing Farsi (Persian) text
Home-page: https://github.com/sinarezaei/farsi_tools
Author: Sina Rezaei
Author-email: sinarezaei1991@gmail.com
License: MIT
Platform: UNKNOWN
Classifier: Programming Language :: Python :: 3
Classifier: License :: OSI Approved :: MIT License
Classifier: Operating System :: OS Independent
Requires-Python: >=3.4
